{
    "/dist/js/app.js": "/dist/js/app.js?id=ffdad5cc180bc057c6e0",
    "/dist/css/screen.css": "/dist/css/screen.css?id=5231a7a992773f92aeed",
    "/dist/css/editor.css": "/dist/css/editor.css?id=ae51ba36bf1e58129fea",
    "/dist/css/customize-controls.css": "/dist/css/customize-controls.css?id=d472c036a437e94a3312",
    "/dist/js/app.js.map": "/dist/js/app.js.map?id=a2e93c728f7280b8f9f2",
    "/dist/css/screen.css.map": "/dist/css/screen.css.map?id=0fa8ab45891c2f995719",
    "/dist/css/editor.css.map": "/dist/css/editor.css.map?id=5292db0aac4dff527c4f",
    "/dist/css/customize-controls.css.map": "/dist/css/customize-controls.css.map?id=29ef8ceaa9c92ad39505",
    "/dist/js/customize-controls.js": "/dist/js/customize-controls.js?id=aed58619b0db7a2c460f",
    "/dist/js/customize-controls.js.map": "/dist/js/customize-controls.js.map?id=1d4869eea315b978cf2c",
    "/dist/js/customize-preview.js": "/dist/js/customize-preview.js?id=dc1123b18df6f679e90d",
    "/dist/js/customize-preview.js.map": "/dist/js/customize-preview.js.map?id=ff392adc8b285bda4f38",
    "/dist/js/editor.js": "/dist/js/editor.js?id=4bfea2e67b4838dec818",
    "/dist/js/editor.js.map": "/dist/js/editor.js.map?id=ce0aa97a51b3ea61723c"
}
